bat/__init__.py
bat/data_generator.py
bat/dataframe_cache.py
bat/dataframe_stats.py
bat/dataframe_to_matrix.py
bat/live_simulator.py
bat/log_to_dataframe.py
bat/log_to_sparkdf.py
bat/zeek_log_reader.py
bat/zeek_multi_log_reader.py
bat/utils/__init__.py
bat/utils/cache.py
bat/utils/compat.py
bat/utils/dir_watcher.py
bat/utils/file_storage.py
bat/utils/file_tailer.py
bat/utils/file_utils.py
bat/utils/geo_lookup.py
bat/utils/net_utils.py
bat/utils/ngrams.py
bat/utils/plot_utils.py
bat/utils/reverse_dns.py
bat/utils/signal_utils.py
bat/utils/vt_query.py
bat-0.3.9.data/data/data/app_stats.log
bat-0.3.9.data/data/data/conn.log
bat-0.3.9.data/data/data/dhcp.log
bat-0.3.9.data/data/data/dhcp.log.gz
bat-0.3.9.data/data/data/dhcp_002.log
bat-0.3.9.data/data/data/dhcp_002.log.gz
bat-0.3.9.data/data/data/dns.log
bat-0.3.9.data/data/data/files.log
bat-0.3.9.data/data/data/ftp.log
bat-0.3.9.data/data/data/http.log
bat-0.3.9.data/data/data/http.log.gz
bat-0.3.9.data/data/data/http_empty.log
bat-0.3.9.data/data/data/notice.log
bat-0.3.9.data/data/data/smtp.log
bat-0.3.9.data/data/data/ssl.log
bat-0.3.9.data/data/data/tor_ssl.log
bat-0.3.9.data/data/data/weird.log
bat-0.3.9.data/data/data/x509.log
bat-0.3.9.data/data/examples/anomaly_detection.py
bat-0.3.9.data/data/examples/anomaly_detection_streaming.py
bat-0.3.9.data/data/examples/cert_checker.py
bat-0.3.9.data/data/examples/file_log_vtquery.py
bat-0.3.9.data/data/examples/http_user_agents.py
bat-0.3.9.data/data/examples/kafka_print.py
bat-0.3.9.data/data/examples/kafka_risky_dns.py
bat-0.3.9.data/data/examples/kafka_spark.py
bat-0.3.9.data/data/examples/risky_dns.py
bat-0.3.9.data/data/examples/tor_and_port_count.py
bat-0.3.9.data/data/examples/yara_matches.py
bat-0.3.9.data/data/examples/zeek_pprint.py
bat-0.3.9.data/data/examples/zeek_to_pandas.py
bat-0.3.9.data/data/examples/zeek_to_parquet.py
bat-0.3.9.data/data/examples/zeek_to_scikit.py
bat-0.3.9.data/data/examples/yara_test/README.md
bat-0.3.9.dist-info/LICENSE
bat-0.3.9.dist-info/METADATA
bat-0.3.9.dist-info/WHEEL
bat-0.3.9.dist-info/top_level.txt
bat-0.3.9.dist-info/RECORD
